aimu/__init__.py
aimu/memory.py
aimu/paths.py
aimu/models/__init__.py
aimu/models/base_client.py
aimu/models/aisuite/__init__.py
aimu/models/aisuite/aisuite_client.py
aimu/models/hf/__init__.py
aimu/models/hf/hf_client.py
aimu/models/ollama/__init__.py
aimu/models/ollama/ollama_client.py
aimu/prompts/__init__.py
aimu/prompts/catalog.py
aimu/prompts/classification.py
aimu/tools/__init__.py
aimu/tools/client.py
aimu/tools/servers.py
aimu-0.1.6.dist-info/licenses/LICENSE
aimu-0.1.6.dist-info/METADATA
aimu-0.1.6.dist-info/WHEEL
aimu-0.1.6.dist-info/top_level.txt
aimu-0.1.6.dist-info/RECORD
