Metadata-Version: 2.4
Name: aimu
Version: 0.1.6
Summary: A Python package containing tools for working with various language models and AI services.
License:                                  Apache License
Requires-Python: >=3.10
License-File: LICENSE
Requires-Dist: sqlalchemy
Requires-Dist: chromadb
Requires-Dist: fastmcp
Requires-Dist: nest_asyncio
Requires-Dist: streamlit
Requires-Dist: watchdog
Requires-Dist: tinydb
Provides-Extra: dev
Requires-Dist: ruff; extra == "dev"
Requires-Dist: pytest; extra == "dev"
Provides-Extra: notebooks
Requires-Dist: ipykernel; extra == "notebooks"
Requires-Dist: ipywidgets; extra == "notebooks"
Provides-Extra: hf
Requires-Dist: torch; extra == "hf"
Requires-Dist: transformers; extra == "hf"
Requires-Dist: accelerate; extra == "hf"
Requires-Dist: sentencepiece; extra == "hf"
Requires-Dist: kernels; extra == "hf"
Provides-Extra: ollama
Requires-Dist: ollama; extra == "ollama"
Provides-Extra: aisuite
Requires-Dist: aisuite[openai]; extra == "aisuite"
Requires-Dist: docstring-parser; extra == "aisuite"
Requires-Dist: python-dotenv; extra == "aisuite"
Provides-Extra: all
Requires-Dist: aimu[aisuite,hf,ollama]; extra == "all"
Dynamic: license-file
